translation_finder/__init__.py
translation_finder/api.py
translation_finder/data.py
translation_finder/finder.py
translation_finder/test_api.py
translation_finder/test_discovery.py
translation_finder/test_finder.py
translation_finder/test_results.py
translation_finder/discovery/__init__.py
translation_finder/discovery/base.py
translation_finder/discovery/files.py
translation_finder/discovery/result.py
translation_finder/discovery/transifex.py
translation_finder/test_data/calibre.txt
translation_finder/test_data/catalysm.txt
translation_finder/test_data/.tx/config
translation_finder/test_data/app/src/res/main/values/strings.xml
translation_finder/test_data/app/src/res/main/values-it/strings.xml
translation_finder/test_data/java/iso.properties
translation_finder/test_data/java/iso_cs.properties
translation_finder/test_data/java/utf-16.properties
translation_finder/test_data/java/utf-16_cs.properties
translation_finder/test_data/java/utf-8.properties
translation_finder/test_data/java/utf-8_cs.properties
translation_finder/test_data/json/bi-cs.json
translation_finder/test_data/json/bom-en.json
translation_finder/test_data/json/flat-en.json
translation_finder/test_data/json/go-cs.json
translation_finder/test_data/json/go-en.json
translation_finder/test_data/json/gotext-en.json
translation_finder/test_data/json/i18next-en.json
translation_finder/test_data/json/i18nextv4-en.json
translation_finder/test_data/json/nested-en.json
translation_finder/test_data/json/webext-en.json
translation_finder/test_data/laravel/en.php
translation_finder/test_data/linked/cs.po
translation_finder/test_data/linked/de.po
translation_finder/test_data/linked/messages.pot
translation_finder/test_data/locales/cs.po
translation_finder/test_data/locales/de.po
translation_finder/test_data/locales/messages.pot
translation_finder/test_data/monopo/cs.po
translation_finder/test_data/monopo/de.po
translation_finder/test_data/monopo/en.po
translation_finder/test_data/php/en.php
translate_finder-2.17.dist-info/LICENSE
translate_finder-2.17.dist-info/METADATA
translate_finder-2.17.dist-info/WHEEL
translate_finder-2.17.dist-info/entry_points.txt
translate_finder-2.17.dist-info/top_level.txt
translate_finder-2.17.dist-info/RECORD
