Metadata-Version: 2.1
Name: translate-finder
Version: 2.17
Summary: A translation file finder used in Deepsquads.
Home-page: https://deepsquads.github.io/
Download-URL: https://github.com/Deepsquads/translate-finder
Author: khulnasoft-bot
Author-email: michal@cihar.com
License: GPL-3.0-or-later
Project-URL: Issue Tracker, https://github.com/Deepsquads/translate-finder/issues
Project-URL: Documentation, https://docs.deepsquads.github.io/
Project-URL: Source Code, https://github.com/Deepsquads/translate-finder
Project-URL: Twitter, https://twitter.com/Deepsquads
Project-URL: Funding, https://deepsquads.github.io/donate/
Keywords: i18n l10n gettext translate
Platform: any
Classifier: Development Status :: 5 - Production/Stable
Classifier: Intended Audience :: Developers
Classifier: License :: OSI Approved :: GNU General Public License v3 or later (GPLv3+)
Classifier: Operating System :: OS Independent
Classifier: Programming Language :: Python
Classifier: Programming Language :: Python :: 3
Classifier: Programming Language :: Python :: 3 :: Only
Classifier: Topic :: Software Development :: Internationalization
Classifier: Topic :: Software Development :: Localization
Classifier: Topic :: Utilities
Requires-Python: >=3.9
License-File: LICENSE
Requires-Dist: charset-normalizer <4.0,>2.0
Requires-Dist: ruamel.yaml
Requires-Dist: deepsquads-language-data >=2021.2
